strot/__init__.py
strot/exceptions.py
strot/llm.py
strot/analyzer/__init__.py
strot/analyzer/analyzer.py
strot/analyzer/prompts/__init__.py
strot/analyzer/prompts/schema.py
strot/analyzer/prompts/templates/analyze_current_view.jinja
strot/analyzer/prompts/templates/generate_extraction_code.jinja
strot/analyzer/prompts/templates/parameter_detection.jinja
strot/browser/__init__.py
strot/browser/inject.js
strot/browser/plugin.py
strot/browser/tab.py
strot/code_executor/__init__.py
strot/code_executor/base.py
strot/code_executor/e2b.py
strot/code_executor/unsafe/__init__.py
strot/code_executor/unsafe/code_meta.py
strot/code_executor/unsafe/executor.py
strot/logging/__init__.py
strot/logging/handlers/__init__.py
strot/logging/handlers/file.py
strot/logging/handlers/s3.py
strot/pagination_translators/__init__.py
strot/pagination_translators/base.py
strot/pagination_translators/limit_offset.py
strot/schema/__init__.py
strot/schema/base.py
strot/schema/pattern.py
strot/schema/point.py
strot/schema/source.py
strot/schema/request/__init__.py
strot/schema/request/detail.py
strot/schema/request/pagination_info.py
strot/schema/request/request.py
strot/schema/response/__init__.py
strot/schema/response/detail.py
strot/schema/response/preprocessor.py
strot/schema/response/response.py
strot/type_adapter/__init__.py
strot/type_adapter/utils.py
strot/utils/__init__.py
strot/utils/image.py
strot/utils/request.py
strot/utils/text.py
strot-1.4.0.dist-info/METADATA
strot-1.4.0.dist-info/WHEEL
strot-1.4.0.dist-info/entry_points.txt
strot-1.4.0.dist-info/licenses/LICENSE
strot-1.4.0.dist-info/RECORD
