Metadata-Version: 2.4
Name: strot
Version: 1.4.0
Summary: Discover API endpoints with natural language
Project-URL: Repository, https://github.com/vertexcover-io/strot
Author-email: Harsh Verma <harsh@vertexcover.io>
License-File: LICENSE
Keywords: python
Classifier: Intended Audience :: Developers
Classifier: Programming Language :: Python
Classifier: Programming Language :: Python :: 3
Classifier: Programming Language :: Python :: 3.10
Classifier: Programming Language :: Python :: 3.11
Classifier: Programming Language :: Python :: 3.12
Classifier: Programming Language :: Python :: 3.13
Classifier: Topic :: Software Development :: Libraries :: Python Modules
Requires-Python: <4.0,>=3.10
Requires-Dist: anthropic>=0.50.0
Requires-Dist: beautifulsoup4>=4.13.4
Requires-Dist: boto3>=1.39.4
Requires-Dist: docstring-parser>=0.17.0
Requires-Dist: e2b-code-interpreter>=2.0.0
Requires-Dist: httpx>=0.28.1
Requires-Dist: jinja2>=3.1.6
Requires-Dist: json-repair>=0.44.1
Requires-Dist: jsonref>=1.1.0
Requires-Dist: openai>=1.76.0
Requires-Dist: patchright<1.53,>=1.52.0
Requires-Dist: pillow>=11.2.1
Requires-Dist: pydantic>=2.11.3
Requires-Dist: python-magic>=0.4.27
Requires-Dist: python-multipart>=0.0.20
Requires-Dist: rapidfuzz>=3.13.0
Requires-Dist: regex>=2024.11.6
Requires-Dist: rnet>=2.4.2
Requires-Dist: structlog>=25.4.0
